thermonuclearpackage/__init__.py
thermonuclearpackage/strikemissile.py
thermonuclearpackage-0.1.2.dist-info/METADATA
thermonuclearpackage-0.1.2.dist-info/WHEEL
thermonuclearpackage-0.1.2.dist-info/top_level.txt
thermonuclearpackage-0.1.2.dist-info/RECORD
